oae5/__init__.py
oae5/functions.py
oae5-0.1.4.dist-info/METADATA
oae5-0.1.4.dist-info/WHEEL
oae5-0.1.4.dist-info/top_level.txt
oae5-0.1.4.dist-info/RECORD
